apminsight/__init__.py
apminsight/agent.py
apminsight/agentfactory.py
apminsight/constants.py
apminsight/context.py
apminsight/custom_api.py
apminsight/logger.py
apminsight/util.py
apminsight/bootstrap/__init__.py
apminsight/bootstrap/sitecustomize.py
apminsight/collector/__init__.py
apminsight/collector/connhandler.py
apminsight/collector/datahandler.py
apminsight/collector/ins_info.py
apminsight/collector/metric_dispatcher.py
apminsight/collector/reqhandler.py
apminsight/collector/rescodes.py
apminsight/collector/reshandler.py
apminsight/commands/__init__.py
apminsight/commands/apm_run.py
apminsight/common/__init__.py
apminsight/common/scheduler.py
apminsight/config/__init__.py
apminsight/config/auto_profiler.py
apminsight/config/config_util.py
apminsight/config/configuration.py
apminsight/config/cpu_usage.py
apminsight/config/encryption.py
apminsight/config/host_env_identifier.py
apminsight/config/threshold.py
apminsight/contrib/__init__.py
apminsight/contrib/django/__init__.py
apminsight/contrib/django/apps.py
apminsight/contrib/django/wrapper.py
apminsight/instrumentation/__init__.py
apminsight/instrumentation/custom_instrument.py
apminsight/instrumentation/dbapi2.py
apminsight/instrumentation/http_util.py
apminsight/instrumentation/instrument.py
apminsight/instrumentation/patch.py
apminsight/instrumentation/proxy.py
apminsight/instrumentation/util.py
apminsight/instrumentation/wrapper.py
apminsight/instrumentation/packages/__init__.py
apminsight/instrumentation/packages/aiomysql.py
apminsight/instrumentation/packages/aioredis.py
apminsight/instrumentation/packages/aredis.py
apminsight/instrumentation/packages/async_cron.py
apminsight/instrumentation/packages/asyncpg.py
apminsight/instrumentation/packages/bottle.py
apminsight/instrumentation/packages/cassandra.py
apminsight/instrumentation/packages/celery.py
apminsight/instrumentation/packages/cheroot.py
apminsight/instrumentation/packages/cherrypy.py
apminsight/instrumentation/packages/concurrent_futures.py
apminsight-1.7.0.dist-info/licenses/LICENSE.txt
apminsight-1.7.0.dist-info/METADATA
apminsight-1.7.0.dist-info/WHEEL
apminsight-1.7.0.dist-info/entry_points.txt
apminsight-1.7.0.dist-info/top_level.txt
apminsight-1.7.0.dist-info/RECORD
