Metadata-Version: 2.4
Name: apminsight
Version: 1.7.0
Summary: Site24x7 application performance monitoring
Home-page: https://site24x7.com
Author: Zoho Corporation Pvt. Ltd.
Author-email: apm-insight@zohocorp.com
Maintainer: ManageEngine Site24x7
Maintainer-email: apm-insight@zohocorp.com
License: LICENSE.txt
Requires-Python: >=3.7
License-File: LICENSE.txt
Requires-Dist: psutil
Dynamic: author
Dynamic: author-email
Dynamic: description
Dynamic: description-content-type
Dynamic: home-page
Dynamic: license
Dynamic: license-file
Dynamic: maintainer
Dynamic: maintainer-email
Dynamic: requires-dist
Dynamic: requires-python
Dynamic: summary
